Metadata-Version: 2.1
Name: byte-converter
Version: 0.1.1
Summary: Translate python objects to bytes.
Home-page: https://github.com/AdriBloober/ByteConverter
Author: AdriBloober
Author-email: adrianbloober@gmail.com
License: UNKNOWN
Platform: UNKNOWN
Classifier: Programming Language :: Python :: 3
Classifier: License :: OSI Approved :: MIT License
Classifier: Operating System :: OS Independent
Requires-Python: >=3.6
